odoo/addons/l10n_jp_address_layout/README.rst
odoo/addons/l10n_jp_address_layout/__init__.py
odoo/addons/l10n_jp_address_layout/__manifest__.py
odoo/addons/l10n_jp_address_layout/data/res_country_data.xml
odoo/addons/l10n_jp_address_layout/i18n/ja_JP.po
odoo/addons/l10n_jp_address_layout/static/description/icon.png
odoo/addons/l10n_jp_address_layout/views/res_partner_views.xml
odoo11_addon_l10n_jp_address_layout-11.0.1.0.0.dist-info/DESCRIPTION.rst
odoo11_addon_l10n_jp_address_layout-11.0.1.0.0.dist-info/METADATA
odoo11_addon_l10n_jp_address_layout-11.0.1.0.0.dist-info/RECORD
odoo11_addon_l10n_jp_address_layout-11.0.1.0.0.dist-info/WHEEL
odoo11_addon_l10n_jp_address_layout-11.0.1.0.0.dist-info/metadata.json
odoo11_addon_l10n_jp_address_layout-11.0.1.0.0.dist-info/top_level.txt
